hpo3-1.5.1.dist-info/METADATA
hpo3-1.5.1.dist-info/WHEEL
pyhpo/__init__.py
pyhpo/__init__.pyi
pyhpo/annotations.py
pyhpo/annotations/__init__.pyi
pyhpo/helper.py
pyhpo/helper/__init__.pyi
pyhpo/pyhpo.cpython-310-aarch64-linux-gnu.so
pyhpo/set.py
pyhpo/stats.py
pyhpo/stats/__init__.pyi
pyhpo/types.py
pyhpo/types/__init__.pyi
hpo3-1.5.1.dist-info/RECORD
