Metadata-Version: 2.4
Name: hpo3
Version: 1.5.1
Classifier: Programming Language :: Rust
Classifier: Programming Language :: Python :: Implementation :: CPython
Classifier: Programming Language :: Python :: Implementation :: PyPy
Classifier: Intended Audience :: Developers
Classifier: Intended Audience :: Healthcare Industry
Classifier: Intended Audience :: Science/Research
Classifier: License :: OSI Approved :: MIT License
Classifier: Operating System :: OS Independent
Classifier: Topic :: Scientific/Engineering :: Bio-Informatics
Classifier: Topic :: Scientific/Engineering :: Medical Science Apps.
Classifier: Topic :: Software Development :: Libraries :: Python Modules
Summary: A Python package to work with the HPO Ontology using a Rust backend for faster performance
Keywords: hpo,phenotype,genotype,bioinformatics,rare diseases
Author-email: Jonas Marcello <jonas.marcello@esbme.com>
License: MIT
Requires-Python: >=3.7
Project-URL: Homepage, https://github.com/anergictcell/hpo3
Project-URL: Repository, https://github.com/anergictcell/hpo3
Project-URL: Bug Tracker, https://github.com/anergictcell/hpo3/issues
Project-URL: Documentation, https://hpo3.readthedocs.io/
